firekit/__init__.py
firekit/evaluate.py
firekit/predict.py
firekit/preprocess.py
firekit/utils.py
firekit/train/__init__.py
firekit/train/metrics.py
firekit/train/trainer.py
firekit/vision/__init__.py
firekit/vision/imagedatasets.py
firekit/vision/transforms.py
firekit-0.0.11.dist-info/METADATA
firekit-0.0.11.dist-info/WHEEL
firekit-0.0.11.dist-info/licenses/LICENSE
firekit-0.0.11.dist-info/RECORD
