Metadata-Version: 2.1
Name: firekit
Version: 0.0.11
Summary: A library of classes and functions for working with PyTorch.
Project-URL: Homepage, https://github.com/olihawkins/firekit
Project-URL: Bug Tracker, https://github.com/olihawkins/firekit/issues
Author-email: Oliver Hawkins <oli@olihawkins.com>
License: ISC License (ISC)
License-File: LICENSE
Classifier: License :: OSI Approved :: ISC License (ISCL)
Classifier: Operating System :: OS Independent
Classifier: Programming Language :: Python :: 3
Requires-Python: >=3.7
Requires-Dist: numpy
Requires-Dist: pandas
Requires-Dist: scikit-learn
Requires-Dist: torch
Requires-Dist: torchvision
